DESCRIPTION.md
LICENSE
MANIFEST.in
README.md
setup.cfg
setup.py
hydroid/HYDROIDexp.py
hydroid/HYDROIDpred.py
hydroid/VERSION
hydroid/__init__.py
hydroid/command_line.py
hydroid.egg-info/PKG-INFO
hydroid.egg-info/SOURCES.txt
hydroid.egg-info/dependency_links.txt
hydroid.egg-info/entry_points.txt
hydroid.egg-info/not-zip-safe
hydroid.egg-info/requires.txt
hydroid.egg-info/top_level.txt
hydroid/pkgdata/amber10_rmin.config
hydroid/pkgdata/charmm36_rmin.config
hydroid/pkgdata/cnr.otf
hydroid/pkgdata/cnrb.otf
hydroid/pkgdata/test_data/lane_config.csv
hydroid/pkgdata/test_data/lane_profiles.xls
hydroid/pkgdata/test_data/test.pdb