Metadata-Version: 1.2
Name: hydroid
Version: 0.0.9
Summary: HYDROID (HYDroxyl-Radical fOotprinting Interpretation for DNA) is a python package for the analysis of experimental data generated by hydroxyl-radical footprinting (HRF) of DNA-protein complexes
Home-page: https://github.com/ncbi/HYDROID
Author: Alexey K. Shaytan, Grigoriy A. Armeev, David Landsman, Anna R. Panchenko
Author-email: alex@intbio.org
License: Public Domain
Keywords: science hydroxyl-radical footprinting image analysis
Platform: UNKNOWN
Classifier: Development Status :: 3 - Alpha
Classifier: Intended Audience :: Science/Research
Classifier: Topic :: Scientific/Engineering :: Bio-Informatics
Classifier: License :: Public Domain
Classifier: Programming Language :: Python :: 2.7
Requires-Python: ==2.7.*
